kydlib/__init__.py
kydlib/kydlib.py
kydlib-0.3.1.dist-info/LICENSE
kydlib-0.3.1.dist-info/METADATA
kydlib-0.3.1.dist-info/WHEEL
kydlib-0.3.1.dist-info/top_level.txt
kydlib-0.3.1.dist-info/RECORD
