Metadata-Version: 2.1
Name: kydlib
Version: 0.3.1
Summary: Routines for exploratory data analysis.
Home-page: https://github.com/afraniomelo/kydlib
Author: Afrânio Melo
Author-email: afraeq@gmail.com
License: MIT
Requires-Python: >=3.7
License-File: LICENSE
Requires-Dist: numpy (>=1.21.6)
Requires-Dist: pandas (>=1.3.5)
Requires-Dist: scipy (>=1.7.3)
Requires-Dist: statsmodels (>=0.13.2)
Requires-Dist: ennemi (>=1.2.0)
Requires-Dist: matplotlib (>=3.5.2)
Requires-Dist: seaborn (>=0.11.2)
Requires-Dist: datashader (>=0.14.1)
Requires-Dist: colorcet (>=3.0.0)
